inkscape_1.3_figures-1.0.8.data/scripts/inkscape-figures
inkscapefigures/__init__.py
inkscapefigures/main.py
inkscapefigures/picker.py
inkscapefigures/template.svg
inkscape_1.3_figures-1.0.8.dist-info/LICENSE
inkscape_1.3_figures-1.0.8.dist-info/METADATA
inkscape_1.3_figures-1.0.8.dist-info/WHEEL
inkscape_1.3_figures-1.0.8.dist-info/top_level.txt
inkscape_1.3_figures-1.0.8.dist-info/RECORD
