Metadata-Version: 2.1
Name: inkscape-1.3-figures
Version: 1.0.8
Summary: Script for managing inkscape figures
Home-page: https://github.com/gillescastel/inkscape-figures
Author: Gilles Castel
Author-email: gilles@castel.dev
License: MIT
Classifier: License :: OSI Approved :: MIT License
Classifier: Programming Language :: Python :: 3
Classifier: Programming Language :: Python :: 3.7
License-File: LICENSE
Requires-Dist: appdirs
Requires-Dist: click
Requires-Dist: daemonize
Requires-Dist: inotify
Requires-Dist: pyperclip
